nuanced/__init__.py
nuanced/cli.py
nuanced/code_graph.py
nuanced/lib/__init__.py
nuanced/lib/call_graph.py
nuanced/lib/utils.py
nuanced-0.1.9.dist-info/METADATA
nuanced-0.1.9.dist-info/WHEEL
nuanced-0.1.9.dist-info/entry_points.txt
nuanced-0.1.9.dist-info/licenses/LICENSE
nuanced-0.1.9.dist-info/RECORD
