Metadata-Version: 2.4
Name: nuanced
Version: 0.1.9
Summary: Nuanced Python
Author-email: Ayman Nadeem <ayman@nuanced.dev>
License-File: LICENSE
Requires-Python: >=3.10
Requires-Dist: jarviscg==0.1.0rc7
Requires-Dist: setuptools>=75.3.0
Requires-Dist: typer>=0.16.0
